tradegym/__init__.py
tradegym/agents/__init__.py
tradegym/agents/baseline.py
tradegym/agents/sb3.py
tradegym/crossval.py
tradegym/rewards.py
tradegym/tradegym.py
tradegym-2024.1.10.dist-info/LICENSE
tradegym-2024.1.10.dist-info/METADATA
tradegym-2024.1.10.dist-info/WHEEL
tradegym-2024.1.10.dist-info/RECORD
