Metadata-Version: 2.1
Name: tradegym
Version: 2024.1.10
Summary: trading gym
License: MIT
Author: Alex-Lekov
Author-email: 61644712+Alex-Lekov@users.noreply.github.com
Requires-Python: >=3.10,<3.11
Classifier: License :: OSI Approved :: MIT License
Classifier: Programming Language :: Python :: 3
Classifier: Programming Language :: Python :: 3.10
Requires-Dist: empyrical (>=0.5.5,<0.6.0)
Requires-Dist: gym (>=0.26.2,<0.27.0)
Requires-Dist: ipykernel (>=6.25.1,<7.0.0)
Requires-Dist: loguru (>=0.7.0,<0.8.0)
Requires-Dist: matplotlib (>=3.7.2,<4.0.0)
Requires-Dist: nbformat (>=5.9.2,<6.0.0)
Requires-Dist: plotly (>=5.16.1,<6.0.0)
Requires-Dist: pytest (>=7.4.0,<8.0.0)
Requires-Dist: pyyaml (>=6.0.1,<7.0.0)
Requires-Dist: quantstats (>=0.0.62,<0.0.63)
Requires-Dist: seaborn (>=0.12.2,<0.13.0)
Requires-Dist: shimmy (>=1.2.1,<2.0.0)
Requires-Dist: stable-baselines3 (>=2.1.0,<3.0.0)
Requires-Dist: torch (>=2.0.0,!=2.0.1)
Requires-Dist: tqdm (>=4.66.1,<5.0.0)
